{
  "unversionedId": "Examples/http",
  "id": "version-0.7.8/Examples/http",
  "isDocsHomePage": false,
  "title": "HTTP",
  "description": "Data",
  "source": "@site/versioned_docs/version-0.7.8/Examples/http.md",
  "sourceDirName": "Examples",
  "slug": "/Examples/http",
  "permalink": "/example-graphql-go/es/docs/0.7.8/Examples/http",
  "editUrl": "https://github.com/LuisIzarra/example-graphql-go/blob/main/versioned_docs/version-0.7.8/Examples/http.md",
  "version": "0.7.8",
  "lastUpdatedAt": 1630538788,
  "formattedLastUpdatedAt": "1/9/2021",
  "sidebarPosition": 8,
  "frontMatter": {
    "sidebar_position": 8
  },
  "sidebar": "version-0.7.8/tutorialSidebar",
  "previous": {
    "title": "HTTP - Post",
    "permalink": "/example-graphql-go/es/docs/0.7.8/Examples/http-post"
  },
  "next": {
    "title": "HTTP Dynamic",
    "permalink": "/example-graphql-go/es/docs/0.7.8/Examples/http-dynamic"
  }
}