{
  "unversionedId": "Examples/context",
  "id": "version-0.8.0/Examples/context",
  "isDocsHomePage": false,
  "title": "Context",
  "description": "`go title=\"main.go\"",
  "source": "@site/versioned_docs/version-0.8.0/Examples/context.md",
  "sourceDirName": "Examples",
  "slug": "/Examples/context",
  "permalink": "/graphql-go.org/docs/Examples/context",
  "editUrl": "https://github.com/graphql-go/graphql-go.org/blob/main/versioned_docs/version-0.8.0/Examples/context.md",
  "version": "0.8.0",
  "lastUpdatedAt": 1539502055,
  "formattedLastUpdatedAt": "10/14/2018",
  "sidebarPosition": 3,
  "frontMatter": {
    "sidebar_position": 3
  },
  "sidebar": "version-0.8.0/tutorialSidebar",
  "previous": {
    "title": "Concurrent Resolvers",
    "permalink": "/graphql-go.org/docs/Examples/concurrent-resolvers"
  },
  "next": {
    "title": "Go GraphQL CRUD Example",
    "permalink": "/graphql-go.org/docs/Examples/crud"
  }
}